lazycli/__init__.py
lazycli/core.py
lazycli-0.6.1.dist-info/DESCRIPTION.rst
lazycli-0.6.1.dist-info/METADATA
lazycli-0.6.1.dist-info/RECORD
lazycli-0.6.1.dist-info/WHEEL
lazycli-0.6.1.dist-info/metadata.json
lazycli-0.6.1.dist-info/top_level.txt
