Metadata-Version: 2.0
Name: lazycli
Version: 0.6.1
Summary: generate command-line interfaces from function signatures
Home-page: https://github.com/ninjaaron/lazycli
License: UNKNOWN
Platform: UNKNOWN
Requires-Python: >=3.5
Requires-Dist: libaaron
